README.md
setup.py
vpl/__init__.py
vpl/__main__.py
vpl/all.py
vpl/basic.py
vpl/defines.py
vpl/fun.py
vpl/io.py
vpl/streaming.py
vpl/util.py
vpl.egg-info/PKG-INFO
vpl.egg-info/SOURCES.txt
vpl.egg-info/dependency_links.txt
vpl.egg-info/requires.txt
vpl.egg-info/top_level.txt
vpl/examples/not_vpl.py
vpl/examples/video.py
vpl/examples/webcam.py