Metadata-Version: 1.1
Name: vpl
Version: 0.0.4
Summary: Video Pipe Line
Home-page: https://github.com/chemicaldevelopment/vpl
Author: Cade Brown
Author-email: cade@chemicaldevelopment.us
License: GPLv3
Keywords: video processing
Platform: UNKNOWN
Classifier: Topic :: Multimedia :: Video :: Conversion
